converito/__init__.py
converito/binary2decimal.py
converito/binary2hexadecimal.py
converito/binary2octal.py
converito/days2hours.py
converito/days2minutes.py
converito/days2months.py
converito/days2seconds.py
converito/days2weeks.py
converito/days2years.py
converito/decimal2binary.py
converito/decimal2hexadecimal.py
converito/decimal2octal.py
converito/hexadecimal2binary.py
converito/hexadecimal2decimal.py
converito/hexadecimal2octal.py
converito/hours2days.py
converito/hours2minutes.py
converito/hours2months.py
converito/hours2seconds.py
converito/hours2weeks.py
converito/hours2years.py
converito/minutes2days.py
converito/minutes2hours.py
converito/minutes2months.py
converito/minutes2seconds.py
converito/minutes2weeks.py
converito/minutes2years.py
converito/months2days.py
converito/months2hours.py
converito/months2minutes.py
converito/months2seconds.py
converito/months2weeks.py
converito/months2years.py
converito/octal2binary.py
converito/octal2decimal.py
converito/octal2hexadecimal.py
converito/seconds2days.py
converito/seconds2hours.py
converito/seconds2minutes.py
converito/seconds2months.py
converito/seconds2weeks.py
converito/seconds2years.py
converito/weeks2days.py
converito/weeks2hours.py
converito/weeks2minutes.py
converito/weeks2months.py
converito/weeks2seconds.py
converito/weeks2years.py
converito/years2days.py
converito/years2hours.py
converito/years2minutes.py
converito/years2months.py
converito/years2seconds.py
converito/years2weeks.py
converito-0.0.2.dist-info/LICENSE.md
converito-0.0.2.dist-info/METADATA
converito-0.0.2.dist-info/WHEEL
converito-0.0.2.dist-info/top_level.txt
converito-0.0.2.dist-info/RECORD
