Metadata-Version: 2.1
Name: converito
Version: 0.0.2
Summary: Converito is a collection of useful functions for developers.
Author-email: Codinasion X <codinasionx@gmail.com>
Project-URL: Homepage, https://github.com/codinasionx/converito
Project-URL: Bug Tracker, https://github.com/codinasionx/converito/issues
Classifier: Programming Language :: Python :: 3
Classifier: License :: OSI Approved :: MIT License
Classifier: Operating System :: OS Independent
Requires-Python: >=3.10
License-File: LICENSE.md
